loghog.py
setup.py
loghog.egg-info/PKG-INFO
loghog.egg-info/SOURCES.txt
loghog.egg-info/dependency_links.txt
loghog.egg-info/top_level.txt