Metadata-Version: 1.1
Name: loghog
Version: 0.7
Summary: LogHog python client
Home-page: https://github.com/activefrequency/loghog
Author: Active Frequency, LLC
Author-email: info@activefrequency.com
License: Apache2
Platform: UNKNOWN
Classifier: Development Status :: 4 - Beta
Classifier: Environment :: Console
Classifier: Intended Audience :: Developers
Classifier: License :: OSI Approved :: Apache Software License
Classifier: Operating System :: MacOS :: MacOS X
Classifier: Operating System :: POSIX
Classifier: Programming Language :: Python
Classifier: Programming Language :: Python :: 3
Classifier: Topic :: Software Development :: Libraries
